ver15/__init__.py
ver15/images/__init__.py
ver15/images/about1.png
ver15/images/cs.png
ver15/images/doc.png
ver15/images/folder_icon.png
ver15/images/initial1.png
ver15/images/java1.png
ver15/images/logo.png
ver15/images/py.png
ver15/requirements/__init__.py
ver15/requirements/requirements.txt
ver15/settings/UT_Settings.ini
ver15/settings/__init__.py
ver15/src/AIUT.py
ver15/src/AIUT_Core_CSharp.py
ver15/src/AIUT_Core_Java.py
ver15/src/AIUT_Core_Python.py
ver15/src/AIUT_SingleFile.py
ver15/src/OpenAI_Pricing.py
ver15/src/__init__.py
ver15/src/sub.py
ver15-0.1.dist-info/METADATA
ver15-0.1.dist-info/WHEEL
ver15-0.1.dist-info/entry_points.txt
ver15-0.1.dist-info/license.txt
ver15-0.1.dist-info/top_level.txt
ver15-0.1.dist-info/RECORD
