Metadata-Version: 2.1
Name: ver15
Version: 0.1
License-File: license.txt
Requires-Dist: Pillow
Requires-Dist: openai ==1.3.5
Requires-Dist: prettytable
